{
  "branches": [
    {
      "id": 1,
      "name": "Sucursal_001",
      "weather_data": {
        "last_updated": "2025-04-15T13:18:37.073353",
        "current_weather": {
          "temperature_str": "17.6°C",
          "weather_code": 3,
          "weather_icon_url": "/static/images/nublado.png"
        },
        "daily_forecast": [
          {
            "formatted_date": "15 abril",
            "weather_code": 45,
            "weather_icon_url": "/static/images/niebla.png",
            "max_temp_str": "17.6°C",
            "min_temp_str": "8.4°C"
          },
          {
            "formatted_date": "16 abril",
            "weather_code": 45,
            "weather_icon_url": "/static/images/niebla.png",
            "max_temp_str": "10.3°C",
            "min_temp_str": "4.2°C"
          },
          {
            "formatted_date": "17 abril",
            "weather_code": 45,
            "weather_icon_url": "/static/images/niebla.png",
            "max_temp_str": "11.8°C",
            "min_temp_str": "3.9°C"
          },
          {
            "formatted_date": "18 abril",
            "weather_code": 3,
            "weather_icon_url": "/static/images/nublado.png",
            "max_temp_str": "9.1°C",
            "min_temp_str": "3.3°C"
          },
          {
            "formatted_date": "19 abril",
            "weather_code": 45,
            "weather_icon_url": "/static/images/niebla.png",
            "max_temp_str": "19.9°C",
            "min_temp_str": "4.5°C"
          },
          {
            "formatted_date": "20 abril",
            "weather_code": 3,
            "weather_icon_url": "/static/images/nublado.png",
            "max_temp_str": "21.9°C",
            "min_temp_str": "8.1°C"
          },
          {
            "formatted_date": "21 abril",
            "weather_code": 3,
            "weather_icon_url": "/static/images/nublado.png",
            "max_temp_str": "22.2°C",
            "min_temp_str": "9.2°C"
          },
          {
            "formatted_date": "22 abril",
            "weather_code": 3,
            "weather_icon_url": "/static/images/nublado.png",
            "max_temp_str": "17.5°C",
            "min_temp_str": "7.0°C"
          }
        ]
      },
      "exchange_rate": {
        "buy": 19.654,
        "sell": 21.332
      }
    },
    {
      "id": 2,
      "name": "Sucursal_002",
      "weather_data": {},
      "exchange_rate": {
        "buy": null,
        "sell": null
      }
    }
  ]
}